{
  "v": "4.8.0",
  "meta": {
    "g": "LottieFiles AE 3.0.2",
    "a": "",
    "k": "",
    "d": "",
    "tc": ""
  },
  "fr": 30,
  "ip": 0,
  "op": 34,
  "w": 1408,
  "h": 360,
  "nm": "TheHuddle_Lottie",
  "ddd": 0,
  "assets": [],
  "layers": [
    {
      "ddd": 0,
      "ind": 1,
      "ty": 4,
      "nm": "the huddle outlines",
      "sr": 1,
      "ks": {
        "o": {
          "a": 0,
          "k": 100,
          "ix": 11
        },
        "r": {
          "a": 0,
          "k": 0,
          "ix": 10
        },
        "p": {
          "a": 0,
          "k": [742.5, 184.288, 0],
          "ix": 2
        },
        "a": {
          "a": 0,
          "k": [660.703, -129.712, 0],
          "ix": 1
        },
        "s": {
          "a": 0,
          "k": [100.5, 100.5, 100],
          "ix": 6
        }
      },
      "ao": 0,
      "shapes": [
        {
          "ty": "gr",
          "it": [
            {
              "ind": 0,
              "ty": "sh",
              "ix": 1,
              "ks": {
                "a": 0,
                "k": {
                  "i": [
                    [0, 0],
                    [0, 0],
                    [0, 0],
                    [0, 0],
                    [0, 0],
                    [0, 0],
                    [0, 0],
                    [0, 0]
                  ],
                  "o": [
                    [0, 0],
                    [0, 0],
                    [0, 0],
                    [0, 0],
                    [0, 0],
                    [0, 0],
                    [0, 0],
                    [0, 0]
                  ],
                  "v": [
                    [40.293, 0],
                    [93.384, 0],
                    [93.384, -228.094],
                    [132.71, -228.094],
                    [132.71, -275.285],
                    [0.966, -275.285],
                    [0.966, -228.094],
                    [40.293, -228.094]
                  ],
                  "c": true
                },
                "ix": 2
              },
              "nm": "t",
              "mn": "ADBE Vector Shape - Group",
              "hd": false
            },
            {
              "ty": "fl",
              "c": {
                "a": 0,
                "k": [0.501949953565, 0.670590030446, 1, 1],
                "ix": 4
              },
              "o": {
                "a": 0,
                "k": 100,
                "ix": 5
              },
              "r": 1,
              "bm": 0,
              "nm": "Fill 1",
              "mn": "ADBE Vector Graphic - Fill",
              "hd": false
            },
            {
              "ty": "st",
              "c": {
                "a": 0,
                "k": [0, 0, 0, 1],
                "ix": 3
              },
              "o": {
                "a": 0,
                "k": 100,
                "ix": 4
              },
              "w": {
                "a": 0,
                "k": 7,
                "ix": 5
              },
              "lc": 1,
              "lj": 1,
              "ml": 4,
              "bm": 0,
              "nm": "Stroke 1",
              "mn": "ADBE Vector Graphic - Stroke",
              "hd": false
            },
            {
              "ty": "tr",
              "p": {
                "a": 0,
                "k": [67.199, -137.992],
                "ix": 2
              },
              "a": {
                "a": 0,
                "k": [67.199, -137.992],
                "ix": 1
              },
              "s": {
                "a": 1,
                "k": [
                  {
                    "i": {
                      "x": [0.149, 0.149],
                      "y": [1, 1]
                    },
                    "o": {
                      "x": [0.333, 0.333],
                      "y": [0, 0]
                    },
                    "t": 0,
                    "s": [0, 0]
                  },
                  {
                    "i": {
                      "x": [0.667, 0.667],
                      "y": [1, 1]
                    },
                    "o": {
                      "x": [1, 1],
                      "y": [0, 0]
                    },
                    "t": 5,
                    "s": [120, 120]
                  },
                  {
                    "i": {
                      "x": [0.667, 0.667],
                      "y": [1, 1]
                    },
                    "o": {
                      "x": [0.333, 0.333],
                      "y": [0, 0]
                    },
                    "t": 10,
                    "s": [90, 90]
                  },
                  {
                    "i": {
                      "x": [0.667, 0.667],
                      "y": [1, 1]
                    },
                    "o": {
                      "x": [0.333, 0.333],
                      "y": [0, 0]
                    },
                    "t": 14,
                    "s": [105, 105]
                  },
                  {
                    "i": {
                      "x": [0.667, 0.667],
                      "y": [0.911, 0.911]
                    },
                    "o": {
                      "x": [0.333, 0.333],
                      "y": [0, 0]
                    },
                    "t": 18,
                    "s": [95, 95]
                  },
                  {
                    "t": 23,
                    "s": [100, 100]
                  }
                ],
                "ix": 3
              },
              "r": {
                "a": 0,
                "k": 0,
                "ix": 6
              },
              "o": {
                "a": 0,
                "k": 100,
                "ix": 7
              },
              "sk": {
                "a": 0,
                "k": 0,
                "ix": 4
              },
              "sa": {
                "a": 0,
                "k": 0,
                "ix": 5
              },
              "nm": "Transform"
            }
          ],
          "nm": "t",
          "np": 3,
          "cix": 2,
          "bm": 0,
          "ix": 1,
          "mn": "ADBE Vector Group",
          "hd": false
        },
        {
          "ty": "gr",
          "it": [
            {
              "ind": 0,
              "ty": "sh",
              "ix": 1,
              "ks": {
                "a": 0,
                "k": {
                  "i": [
                    [0, 0],
                    [0, 0],
                    [0, 0],
                    [0, 0],
                    [0, 0],
                    [0, 0],
                    [0, 0],
                    [0, 0],
                    [0, 0],
                    [0, 0],
                    [0, 0],
                    [0, 0]
                  ],
                  "o": [
                    [0, 0],
                    [0, 0],
                    [0, 0],
                    [0, 0],
                    [0, 0],
                    [0, 0],
                    [0, 0],
                    [0, 0],
                    [0, 0],
                    [0, 0],
                    [0, 0],
                    [0, 0]
                  ],
                  "v": [
                    [137.314, 0],
                    [190.405, 0],
                    [190.405, -114.047],
                    [210.068, -114.047],
                    [210.068, 0],
                    [263.159, 0],
                    [263.159, -275.285],
                    [210.068, -275.285],
                    [210.068, -161.239],
                    [190.405, -161.239],
                    [190.405, -275.285],
                    [137.314, -275.285]
                  ],
                  "c": true
                },
                "ix": 2
              },
              "nm": "h",
              "mn": "ADBE Vector Shape - Group",
              "hd": false
            },
            {
              "ty": "fl",
              "c": {
                "a": 0,
                "k": [0.501949953565, 0.670590030446, 1, 1],
                "ix": 4
              },
              "o": {
                "a": 0,
                "k": 100,
                "ix": 5
              },
              "r": 1,
              "bm": 0,
              "nm": "Fill 1",
              "mn": "ADBE Vector Graphic - Fill",
              "hd": false
            },
            {
              "ty": "st",
              "c": {
                "a": 0,
                "k": [0, 0, 0, 1],
                "ix": 3
              },
              "o": {
                "a": 0,
                "k": 100,
                "ix": 4
              },
              "w": {
                "a": 0,
                "k": 7,
                "ix": 5
              },
              "lc": 1,
              "lj": 1,
              "ml": 4,
              "bm": 0,
              "nm": "Stroke 1",
              "mn": "ADBE Vector Graphic - Stroke",
              "hd": false
            },
            {
              "ty": "tr",
              "p": {
                "a": 0,
                "k": [200.436, -138.048],
                "ix": 2
              },
              "a": {
                "a": 0,
                "k": [200.436, -138.048],
                "ix": 1
              },
              "s": {
                "a": 1,
                "k": [
                  {
                    "i": {
                      "x": [0.149, 0.149],
                      "y": [1, 1]
                    },
                    "o": {
                      "x": [0.333, 0.333],
                      "y": [0, 0]
                    },
                    "t": 1,
                    "s": [0, 0]
                  },
                  {
                    "i": {
                      "x": [0.667, 0.667],
                      "y": [1, 1]
                    },
                    "o": {
                      "x": [1, 1],
                      "y": [0, 0]
                    },
                    "t": 6,
                    "s": [120, 120]
                  },
                  {
                    "i": {
                      "x": [0.667, 0.667],
                      "y": [1, 1]
                    },
                    "o": {
                      "x": [0.333, 0.333],
                      "y": [0, 0]
                    },
                    "t": 11,
                    "s": [90, 90]
                  },
                  {
                    "i": {
                      "x": [0.667, 0.667],
                      "y": [1, 1]
                    },
                    "o": {
                      "x": [0.333, 0.333],
                      "y": [0, 0]
                    },
                    "t": 15,
                    "s": [105, 105]
                  },
                  {
                    "i": {
                      "x": [0.667, 0.667],
                      "y": [0.911, 0.911]
                    },
                    "o": {
                      "x": [0.333, 0.333],
                      "y": [0, 0]
                    },
                    "t": 19,
                    "s": [95, 95]
                  },
                  {
                    "t": 24,
                    "s": [100, 100]
                  }
                ],
                "ix": 3
              },
              "r": {
                "a": 0,
                "k": 0,
                "ix": 6
              },
              "o": {
                "a": 0,
                "k": 100,
                "ix": 7
              },
              "sk": {
                "a": 0,
                "k": 0,
                "ix": 4
              },
              "sa": {
                "a": 0,
                "k": 0,
                "ix": 5
              },
              "nm": "Transform"
            }
          ],
          "nm": "h",
          "np": 3,
          "cix": 2,
          "bm": 0,
          "ix": 2,
          "mn": "ADBE Vector Group",
          "hd": false
        },
        {
          "ty": "gr",
          "it": [
            {
              "ind": 0,
              "ty": "sh",
              "ix": 1,
              "ks": {
                "a": 0,
                "k": {
                  "i": [
                    [0, 0],
                    [0, 0],
                    [0, 0],
                    [0, 0],
                    [0, 0],
                    [0, 0],
                    [0, 0],
                    [0, 0],
                    [0, 0],
                    [0, 0],
                    [0, 0],
                    [0, 0]
                  ],
                  "o": [
                    [0, 0],
                    [0, 0],
                    [0, 0],
                    [0, 0],
                    [0, 0],
                    [0, 0],
                    [0, 0],
                    [0, 0],
                    [0, 0],
                    [0, 0],
                    [0, 0],
                    [0, 0]
                  ],
                  "v": [
                    [277.5, 0],
                    [379.749, 0],
                    [379.749, -47.192],
                    [330.591, -47.192],
                    [330.591, -117.979],
                    [365.984, -117.979],
                    [365.984, -165.171],
                    [330.591, -165.171],
                    [330.591, -228.094],
                    [379.749, -228.094],
                    [379.749, -275.285],
                    [277.5, -275.285]
                  ],
                  "c": true
                },
                "ix": 2
              },
              "nm": "e",
              "mn": "ADBE Vector Shape - Group",
              "hd": false
            },
            {
              "ty": "fl",
              "c": {
                "a": 0,
                "k": [0.501949953565, 0.670590030446, 1, 1],
                "ix": 4
              },
              "o": {
                "a": 0,
                "k": 100,
                "ix": 5
              },
              "r": 1,
              "bm": 0,
              "nm": "Fill 1",
              "mn": "ADBE Vector Graphic - Fill",
              "hd": false
            },
            {
              "ty": "st",
              "c": {
                "a": 0,
                "k": [0, 0, 0, 1],
                "ix": 3
              },
              "o": {
                "a": 0,
                "k": 100,
                "ix": 4
              },
              "w": {
                "a": 0,
                "k": 7,
                "ix": 5
              },
              "lc": 1,
              "lj": 1,
              "ml": 4,
              "bm": 0,
              "nm": "Stroke 1",
              "mn": "ADBE Vector Graphic - Stroke",
              "hd": false
            },
            {
              "ty": "tr",
              "p": {
                "a": 0,
                "k": [328.837, -137.806],
                "ix": 2
              },
              "a": {
                "a": 0,
                "k": [328.837, -137.806],
                "ix": 1
              },
              "s": {
                "a": 1,
                "k": [
                  {
                    "i": {
                      "x": [0.149, 0.149],
                      "y": [1, 1]
                    },
                    "o": {
                      "x": [0.333, 0.333],
                      "y": [0, 0]
                    },
                    "t": 2,
                    "s": [0, 0]
                  },
                  {
                    "i": {
                      "x": [0.667, 0.667],
                      "y": [1, 1]
                    },
                    "o": {
                      "x": [1, 1],
                      "y": [0, 0]
                    },
                    "t": 7,
                    "s": [120, 120]
                  },
                  {
                    "i": {
                      "x": [0.667, 0.667],
                      "y": [1, 1]
                    },
                    "o": {
                      "x": [0.333, 0.333],
                      "y": [0, 0]
                    },
                    "t": 12,
                    "s": [90, 90]
                  },
                  {
                    "i": {
                      "x": [0.667, 0.667],
                      "y": [1, 1]
                    },
                    "o": {
                      "x": [0.333, 0.333],
                      "y": [0, 0]
                    },
                    "t": 16,
                    "s": [105, 105]
                  },
                  {
                    "i": {
                      "x": [0.667, 0.667],
                      "y": [0.911, 0.911]
                    },
                    "o": {
                      "x": [0.333, 0.333],
                      "y": [0, 0]
                    },
                    "t": 20,
                    "s": [95, 95]
                  },
                  {
                    "t": 25,
                    "s": [100, 100]
                  }
                ],
                "ix": 3
              },
              "r": {
                "a": 0,
                "k": 0,
                "ix": 6
              },
              "o": {
                "a": 0,
                "k": 100,
                "ix": 7
              },
              "sk": {
                "a": 0,
                "k": 0,
                "ix": 4
              },
              "sa": {
                "a": 0,
                "k": 0,
                "ix": 5
              },
              "nm": "Transform"
            }
          ],
          "nm": "e",
          "np": 3,
          "cix": 2,
          "bm": 0,
          "ix": 3,
          "mn": "ADBE Vector Group",
          "hd": false
        },
        {
          "ty": "gr",
          "it": [
            {
              "ind": 0,
              "ty": "sh",
              "ix": 1,
              "ks": {
                "a": 0,
                "k": {
                  "i": [
                    [0, 0],
                    [0, 0],
                    [0, 0],
                    [0, 0],
                    [0, 0],
                    [0, 0],
                    [0, 0],
                    [0, 0],
                    [0, 0],
                    [0, 0],
                    [0, 0],
                    [0, 0]
                  ],
                  "o": [
                    [0, 0],
                    [0, 0],
                    [0, 0],
                    [0, 0],
                    [0, 0],
                    [0, 0],
                    [0, 0],
                    [0, 0],
                    [0, 0],
                    [0, 0],
                    [0, 0],
                    [0, 0]
                  ],
                  "v": [
                    [440.726, 0],
                    [493.816, 0],
                    [493.816, -114.047],
                    [513.48, -114.047],
                    [513.48, 0],
                    [566.57, 0],
                    [566.57, -275.285],
                    [513.48, -275.285],
                    [513.48, -161.239],
                    [493.816, -161.239],
                    [493.816, -275.285],
                    [440.726, -275.285]
                  ],
                  "c": true
                },
                "ix": 2
              },
              "nm": "h",
              "mn": "ADBE Vector Shape - Group",
              "hd": false
            },
            {
              "ty": "fl",
              "c": {
                "a": 0,
                "k": [0.501949953565, 0.670590030446, 1, 1],
                "ix": 4
              },
              "o": {
                "a": 0,
                "k": 100,
                "ix": 5
              },
              "r": 1,
              "bm": 0,
              "nm": "Fill 1",
              "mn": "ADBE Vector Graphic - Fill",
              "hd": false
            },
            {
              "ty": "st",
              "c": {
                "a": 0,
                "k": [0, 0, 0, 1],
                "ix": 3
              },
              "o": {
                "a": 0,
                "k": 100,
                "ix": 4
              },
              "w": {
                "a": 0,
                "k": 7,
                "ix": 5
              },
              "lc": 1,
              "lj": 1,
              "ml": 4,
              "bm": 0,
              "nm": "Stroke 1",
              "mn": "ADBE Vector Graphic - Stroke",
              "hd": false
            },
            {
              "ty": "tr",
              "p": {
                "a": 0,
                "k": [503.91, -138.022],
                "ix": 2
              },
              "a": {
                "a": 0,
                "k": [503.91, -138.022],
                "ix": 1
              },
              "s": {
                "a": 1,
                "k": [
                  {
                    "i": {
                      "x": [0.149, 0.149],
                      "y": [1, 1]
                    },
                    "o": {
                      "x": [0.333, 0.333],
                      "y": [0, 0]
                    },
                    "t": 3,
                    "s": [0, 0]
                  },
                  {
                    "i": {
                      "x": [0.667, 0.667],
                      "y": [1, 1]
                    },
                    "o": {
                      "x": [1, 1],
                      "y": [0, 0]
                    },
                    "t": 8,
                    "s": [120, 120]
                  },
                  {
                    "i": {
                      "x": [0.667, 0.667],
                      "y": [1, 1]
                    },
                    "o": {
                      "x": [0.333, 0.333],
                      "y": [0, 0]
                    },
                    "t": 13,
                    "s": [90, 90]
                  },
                  {
                    "i": {
                      "x": [0.667, 0.667],
                      "y": [1, 1]
                    },
                    "o": {
                      "x": [0.333, 0.333],
                      "y": [0, 0]
                    },
                    "t": 17,
                    "s": [105, 105]
                  },
                  {
                    "i": {
                      "x": [0.667, 0.667],
                      "y": [0.911, 0.911]
                    },
                    "o": {
                      "x": [0.333, 0.333],
                      "y": [0, 0]
                    },
                    "t": 21,
                    "s": [95, 95]
                  },
                  {
                    "t": 26,
                    "s": [100, 100]
                  }
                ],
                "ix": 3
              },
              "r": {
                "a": 0,
                "k": 0,
                "ix": 6
              },
              "o": {
                "a": 0,
                "k": 100,
                "ix": 7
              },
              "sk": {
                "a": 0,
                "k": 0,
                "ix": 4
              },
              "sa": {
                "a": 0,
                "k": 0,
                "ix": 5
              },
              "nm": "Transform"
            }
          ],
          "nm": "h",
          "np": 3,
          "cix": 2,
          "bm": 0,
          "ix": 4,
          "mn": "ADBE Vector Group",
          "hd": false
        },
        {
          "ty": "gr",
          "it": [
            {
              "ind": 0,
              "ty": "sh",
              "ix": 1,
              "ks": {
                "a": 0,
                "k": {
                  "i": [
                    [-35.394, 0],
                    [0, 66.855],
                    [0, 0],
                    [0, 0],
                    [0, 0],
                    [5.899, 0],
                    [0, 35.394],
                    [0, 0],
                    [0, 0],
                    [0, 0]
                  ],
                  "o": [
                    [35.394, 0],
                    [0, 0],
                    [0, 0],
                    [0, 0],
                    [0, 35.394],
                    [-5.899, 0],
                    [0, 0],
                    [0, 0],
                    [0, 0],
                    [0, 66.855]
                  ],
                  "v": [
                    [643.833, 5.899],
                    [706.756, -88.485],
                    [706.756, -275.285],
                    [653.665, -275.285],
                    [653.665, -76.687],
                    [643.833, -37.36],
                    [634.002, -76.687],
                    [634.002, -275.285],
                    [580.911, -275.285],
                    [580.911, -88.485]
                  ],
                  "c": true
                },
                "ix": 2
              },
              "nm": "u",
              "mn": "ADBE Vector Shape - Group",
              "hd": false
            },
            {
              "ty": "fl",
              "c": {
                "a": 0,
                "k": [0.501949953565, 0.670590030446, 1, 1],
                "ix": 4
              },
              "o": {
                "a": 0,
                "k": 100,
                "ix": 5
              },
              "r": 1,
              "bm": 0,
              "nm": "Fill 1",
              "mn": "ADBE Vector Graphic - Fill",
              "hd": false
            },
            {
              "ty": "st",
              "c": {
                "a": 0,
                "k": [0, 0, 0, 1],
                "ix": 3
              },
              "o": {
                "a": 0,
                "k": 100,
                "ix": 4
              },
              "w": {
                "a": 0,
                "k": 7,
                "ix": 5
              },
              "lc": 1,
              "lj": 1,
              "ml": 4,
              "bm": 0,
              "nm": "Stroke 1",
              "mn": "ADBE Vector Graphic - Stroke",
              "hd": false
            },
            {
              "ty": "tr",
              "p": {
                "a": 0,
                "k": [644.177, -135.004],
                "ix": 2
              },
              "a": {
                "a": 0,
                "k": [644.177, -135.004],
                "ix": 1
              },
              "s": {
                "a": 1,
                "k": [
                  {
                    "i": {
                      "x": [0.149, 0.149],
                      "y": [1, 1]
                    },
                    "o": {
                      "x": [0.333, 0.333],
                      "y": [0, 0]
                    },
                    "t": 4,
                    "s": [0, 0]
                  },
                  {
                    "i": {
                      "x": [0.667, 0.667],
                      "y": [1, 1]
                    },
                    "o": {
                      "x": [1, 1],
                      "y": [0, 0]
                    },
                    "t": 9,
                    "s": [120, 120]
                  },
                  {
                    "i": {
                      "x": [0.667, 0.667],
                      "y": [1, 1]
                    },
                    "o": {
                      "x": [0.333, 0.333],
                      "y": [0, 0]
                    },
                    "t": 14,
                    "s": [90, 90]
                  },
                  {
                    "i": {
                      "x": [0.667, 0.667],
                      "y": [1, 1]
                    },
                    "o": {
                      "x": [0.333, 0.333],
                      "y": [0, 0]
                    },
                    "t": 18,
                    "s": [105, 105]
                  },
                  {
                    "i": {
                      "x": [0.667, 0.667],
                      "y": [0.911, 0.911]
                    },
                    "o": {
                      "x": [0.333, 0.333],
                      "y": [0, 0]
                    },
                    "t": 22,
                    "s": [95, 95]
                  },
                  {
                    "t": 27,
                    "s": [100, 100]
                  }
                ],
                "ix": 3
              },
              "r": {
                "a": 0,
                "k": 0,
                "ix": 6
              },
              "o": {
                "a": 0,
                "k": 100,
                "ix": 7
              },
              "sk": {
                "a": 0,
                "k": 0,
                "ix": 4
              },
              "sa": {
                "a": 0,
                "k": 0,
                "ix": 5
              },
              "nm": "Transform"
            }
          ],
          "nm": "u",
          "np": 3,
          "cix": 2,
          "bm": 0,
          "ix": 5,
          "mn": "ADBE Vector Group",
          "hd": false
        },
        {
          "ty": "gr",
          "it": [
            {
              "ind": 0,
              "ty": "sh",
              "ix": 1,
              "ks": {
                "a": 0,
                "k": {
                  "i": [
                    [0, 0],
                    [0, 0],
                    [0, 104.215],
                    [43.259, 0],
                    [0, 0]
                  ],
                  "o": [
                    [0, 0],
                    [43.259, 0],
                    [0, -104.215],
                    [0, 0],
                    [0, 0]
                  ],
                  "v": [
                    [721.097, 0],
                    [774.187, 0],
                    [850.874, -137.643],
                    [774.187, -275.285],
                    [721.097, -275.285]
                  ],
                  "c": true
                },
                "ix": 2
              },
              "nm": "d",
              "mn": "ADBE Vector Shape - Group",
              "hd": false
            },
            {
              "ind": 1,
              "ty": "sh",
              "ix": 2,
              "ks": {
                "a": 0,
                "k": {
                  "i": [
                    [0, 0],
                    [0, 0],
                    [0, 0],
                    [0, -86.518],
                    [9.832, 0]
                  ],
                  "o": [
                    [0, 0],
                    [0, 0],
                    [9.832, 0],
                    [0, 86.518],
                    [0, 0]
                  ],
                  "v": [
                    [774.187, -43.259],
                    [774.187, -232.026],
                    [776.154, -232.026],
                    [793.851, -137.643],
                    [776.154, -43.259]
                  ],
                  "c": true
                },
                "ix": 2
              },
              "nm": "d",
              "mn": "ADBE Vector Shape - Group",
              "hd": false
            },
            {
              "ty": "mm",
              "mm": 1,
              "nm": "Merge Paths 1",
              "mn": "ADBE Vector Filter - Merge",
              "hd": false
            },
            {
              "ty": "fl",
              "c": {
                "a": 0,
                "k": [0.501949953565, 0.670590030446, 1, 1],
                "ix": 4
              },
              "o": {
                "a": 0,
                "k": 100,
                "ix": 5
              },
              "r": 1,
              "bm": 0,
              "nm": "Fill 1",
              "mn": "ADBE Vector Graphic - Fill",
              "hd": false
            },
            {
              "ty": "st",
              "c": {
                "a": 0,
                "k": [0, 0, 0, 1],
                "ix": 3
              },
              "o": {
                "a": 0,
                "k": 100,
                "ix": 4
              },
              "w": {
                "a": 0,
                "k": 7,
                "ix": 5
              },
              "lc": 1,
              "lj": 1,
              "ml": 4,
              "bm": 0,
              "nm": "Stroke 1",
              "mn": "ADBE Vector Graphic - Stroke",
              "hd": false
            },
            {
              "ty": "tr",
              "p": {
                "a": 0,
                "k": [785.527, -136.981],
                "ix": 2
              },
              "a": {
                "a": 0,
                "k": [785.527, -136.981],
                "ix": 1
              },
              "s": {
                "a": 1,
                "k": [
                  {
                    "i": {
                      "x": [0.149, 0.149],
                      "y": [1, 1]
                    },
                    "o": {
                      "x": [0.333, 0.333],
                      "y": [0, 0]
                    },
                    "t": 5,
                    "s": [0, 0]
                  },
                  {
                    "i": {
                      "x": [0.667, 0.667],
                      "y": [1, 1]
                    },
                    "o": {
                      "x": [1, 1],
                      "y": [0, 0]
                    },
                    "t": 10,
                    "s": [120, 120]
                  },
                  {
                    "i": {
                      "x": [0.667, 0.667],
                      "y": [1, 1]
                    },
                    "o": {
                      "x": [0.333, 0.333],
                      "y": [0, 0]
                    },
                    "t": 15,
                    "s": [90, 90]
                  },
                  {
                    "i": {
                      "x": [0.667, 0.667],
                      "y": [1, 1]
                    },
                    "o": {
                      "x": [0.333, 0.333],
                      "y": [0, 0]
                    },
                    "t": 19,
                    "s": [105, 105]
                  },
                  {
                    "i": {
                      "x": [0.667, 0.667],
                      "y": [0.911, 0.911]
                    },
                    "o": {
                      "x": [0.333, 0.333],
                      "y": [0, 0]
                    },
                    "t": 23,
                    "s": [95, 95]
                  },
                  {
                    "t": 28,
                    "s": [100, 100]
                  }
                ],
                "ix": 3
              },
              "r": {
                "a": 0,
                "k": 0,
                "ix": 6
              },
              "o": {
                "a": 0,
                "k": 100,
                "ix": 7
              },
              "sk": {
                "a": 0,
                "k": 0,
                "ix": 4
              },
              "sa": {
                "a": 0,
                "k": 0,
                "ix": 5
              },
              "nm": "Transform"
            }
          ],
          "nm": "d",
          "np": 5,
          "cix": 2,
          "bm": 0,
          "ix": 6,
          "mn": "ADBE Vector Group",
          "hd": false
        },
        {
          "ty": "gr",
          "it": [
            {
              "ind": 0,
              "ty": "sh",
              "ix": 1,
              "ks": {
                "a": 0,
                "k": {
                  "i": [
                    [0, 0],
                    [0, 0],
                    [0, 104.215],
                    [43.259, 0],
                    [0, 0]
                  ],
                  "o": [
                    [0, 0],
                    [43.259, 0],
                    [0, -104.215],
                    [0, 0],
                    [0, 0]
                  ],
                  "v": [
                    [861.282, 0],
                    [914.373, 0],
                    [991.059, -137.643],
                    [914.373, -275.285],
                    [861.282, -275.285]
                  ],
                  "c": true
                },
                "ix": 2
              },
              "nm": "d",
              "mn": "ADBE Vector Shape - Group",
              "hd": false
            },
            {
              "ind": 1,
              "ty": "sh",
              "ix": 2,
              "ks": {
                "a": 0,
                "k": {
                  "i": [
                    [0, 0],
                    [0, 0],
                    [0, 0],
                    [0, -86.518],
                    [9.832, 0]
                  ],
                  "o": [
                    [0, 0],
                    [0, 0],
                    [9.832, 0],
                    [0, 86.518],
                    [0, 0]
                  ],
                  "v": [
                    [914.373, -43.259],
                    [914.373, -232.026],
                    [916.339, -232.026],
                    [934.036, -137.643],
                    [916.339, -43.259]
                  ],
                  "c": true
                },
                "ix": 2
              },
              "nm": "d",
              "mn": "ADBE Vector Shape - Group",
              "hd": false
            },
            {
              "ty": "mm",
              "mm": 1,
              "nm": "Merge Paths 1",
              "mn": "ADBE Vector Filter - Merge",
              "hd": false
            },
            {
              "ty": "fl",
              "c": {
                "a": 0,
                "k": [0.501949953565, 0.670590030446, 1, 1],
                "ix": 4
              },
              "o": {
                "a": 0,
                "k": 100,
                "ix": 5
              },
              "r": 1,
              "bm": 0,
              "nm": "Fill 1",
              "mn": "ADBE Vector Graphic - Fill",
              "hd": false
            },
            {
              "ty": "st",
              "c": {
                "a": 0,
                "k": [0, 0, 0, 1],
                "ix": 3
              },
              "o": {
                "a": 0,
                "k": 100,
                "ix": 4
              },
              "w": {
                "a": 0,
                "k": 7,
                "ix": 5
              },
              "lc": 1,
              "lj": 1,
              "ml": 4,
              "bm": 0,
              "nm": "Stroke 1",
              "mn": "ADBE Vector Graphic - Stroke",
              "hd": false
            },
            {
              "ty": "tr",
              "p": {
                "a": 0,
                "k": [925.836, -136.928],
                "ix": 2
              },
              "a": {
                "a": 0,
                "k": [925.836, -136.928],
                "ix": 1
              },
              "s": {
                "a": 1,
                "k": [
                  {
                    "i": {
                      "x": [0.149, 0.149],
                      "y": [1, 1]
                    },
                    "o": {
                      "x": [0.333, 0.333],
                      "y": [0, 0]
                    },
                    "t": 6,
                    "s": [0, 0]
                  },
                  {
                    "i": {
                      "x": [0.667, 0.667],
                      "y": [1, 1]
                    },
                    "o": {
                      "x": [1, 1],
                      "y": [0, 0]
                    },
                    "t": 11,
                    "s": [120, 120]
                  },
                  {
                    "i": {
                      "x": [0.667, 0.667],
                      "y": [1, 1]
                    },
                    "o": {
                      "x": [0.333, 0.333],
                      "y": [0, 0]
                    },
                    "t": 16,
                    "s": [90, 90]
                  },
                  {
                    "i": {
                      "x": [0.667, 0.667],
                      "y": [1, 1]
                    },
                    "o": {
                      "x": [0.333, 0.333],
                      "y": [0, 0]
                    },
                    "t": 20,
                    "s": [105, 105]
                  },
                  {
                    "i": {
                      "x": [0.667, 0.667],
                      "y": [0.911, 0.911]
                    },
                    "o": {
                      "x": [0.333, 0.333],
                      "y": [0, 0]
                    },
                    "t": 24,
                    "s": [95, 95]
                  },
                  {
                    "t": 29,
                    "s": [100, 100]
                  }
                ],
                "ix": 3
              },
              "r": {
                "a": 0,
                "k": 0,
                "ix": 6
              },
              "o": {
                "a": 0,
                "k": 100,
                "ix": 7
              },
              "sk": {
                "a": 0,
                "k": 0,
                "ix": 4
              },
              "sa": {
                "a": 0,
                "k": 0,
                "ix": 5
              },
              "nm": "Transform"
            }
          ],
          "nm": "d",
          "np": 5,
          "cix": 2,
          "bm": 0,
          "ix": 7,
          "mn": "ADBE Vector Group",
          "hd": false
        },
        {
          "ty": "gr",
          "it": [
            {
              "ind": 0,
              "ty": "sh",
              "ix": 1,
              "ks": {
                "a": 0,
                "k": {
                  "i": [
                    [0, 0],
                    [0, 0],
                    [0, 0],
                    [0, 0],
                    [0, 0],
                    [0, 0]
                  ],
                  "o": [
                    [0, 0],
                    [0, 0],
                    [0, 0],
                    [0, 0],
                    [0, 0],
                    [0, 0]
                  ],
                  "v": [
                    [1001.468, 0],
                    [1105.683, 0],
                    [1105.683, -47.192],
                    [1054.558, -47.192],
                    [1054.558, -275.285],
                    [1001.468, -275.285]
                  ],
                  "c": true
                },
                "ix": 2
              },
              "nm": "l",
              "mn": "ADBE Vector Shape - Group",
              "hd": false
            },
            {
              "ty": "fl",
              "c": {
                "a": 0,
                "k": [0.501949953565, 0.670590030446, 1, 1],
                "ix": 4
              },
              "o": {
                "a": 0,
                "k": 100,
                "ix": 5
              },
              "r": 1,
              "bm": 0,
              "nm": "Fill 1",
              "mn": "ADBE Vector Graphic - Fill",
              "hd": false
            },
            {
              "ty": "st",
              "c": {
                "a": 0,
                "k": [0, 0, 0, 1],
                "ix": 3
              },
              "o": {
                "a": 0,
                "k": 100,
                "ix": 4
              },
              "w": {
                "a": 0,
                "k": 7,
                "ix": 5
              },
              "lc": 1,
              "lj": 1,
              "ml": 4,
              "bm": 0,
              "nm": "Stroke 1",
              "mn": "ADBE Vector Graphic - Stroke",
              "hd": false
            },
            {
              "ty": "tr",
              "p": {
                "a": 0,
                "k": [1053.117, -137.015],
                "ix": 2
              },
              "a": {
                "a": 0,
                "k": [1053.117, -137.015],
                "ix": 1
              },
              "s": {
                "a": 1,
                "k": [
                  {
                    "i": {
                      "x": [0.149, 0.149],
                      "y": [1, 1]
                    },
                    "o": {
                      "x": [0.333, 0.333],
                      "y": [0, 0]
                    },
                    "t": 7,
                    "s": [0, 0]
                  },
                  {
                    "i": {
                      "x": [0.667, 0.667],
                      "y": [1, 1]
                    },
                    "o": {
                      "x": [1, 1],
                      "y": [0, 0]
                    },
                    "t": 12,
                    "s": [120, 120]
                  },
                  {
                    "i": {
                      "x": [0.667, 0.667],
                      "y": [1, 1]
                    },
                    "o": {
                      "x": [0.333, 0.333],
                      "y": [0, 0]
                    },
                    "t": 17,
                    "s": [90, 90]
                  },
                  {
                    "i": {
                      "x": [0.667, 0.667],
                      "y": [1, 1]
                    },
                    "o": {
                      "x": [0.333, 0.333],
                      "y": [0, 0]
                    },
                    "t": 21,
                    "s": [105, 105]
                  },
                  {
                    "i": {
                      "x": [0.667, 0.667],
                      "y": [0.911, 0.911]
                    },
                    "o": {
                      "x": [0.333, 0.333],
                      "y": [0, 0]
                    },
                    "t": 25,
                    "s": [95, 95]
                  },
                  {
                    "t": 30,
                    "s": [100, 100]
                  }
                ],
                "ix": 3
              },
              "r": {
                "a": 0,
                "k": 0,
                "ix": 6
              },
              "o": {
                "a": 0,
                "k": 100,
                "ix": 7
              },
              "sk": {
                "a": 0,
                "k": 0,
                "ix": 4
              },
              "sa": {
                "a": 0,
                "k": 0,
                "ix": 5
              },
              "nm": "Transform"
            }
          ],
          "nm": "l",
          "np": 3,
          "cix": 2,
          "bm": 0,
          "ix": 8,
          "mn": "ADBE Vector Group",
          "hd": false
        },
        {
          "ty": "gr",
          "it": [
            {
              "ind": 0,
              "ty": "sh",
              "ix": 1,
              "ks": {
                "a": 0,
                "k": {
                  "i": [
                    [0, 0],
                    [0, 0],
                    [0, 0],
                    [0, 0],
                    [0, 0],
                    [0, 0],
                    [0, 0],
                    [0, 0],
                    [0, 0],
                    [0, 0],
                    [0, 0],
                    [0, 0]
                  ],
                  "o": [
                    [0, 0],
                    [0, 0],
                    [0, 0],
                    [0, 0],
                    [0, 0],
                    [0, 0],
                    [0, 0],
                    [0, 0],
                    [0, 0],
                    [0, 0],
                    [0, 0],
                    [0, 0]
                  ],
                  "v": [
                    [1110.412, 0],
                    [1212.661, 0],
                    [1212.661, -47.192],
                    [1163.503, -47.192],
                    [1163.503, -117.979],
                    [1198.897, -117.979],
                    [1198.897, -165.171],
                    [1163.503, -165.171],
                    [1163.503, -228.094],
                    [1212.661, -228.094],
                    [1212.661, -275.285],
                    [1110.412, -275.285]
                  ],
                  "c": true
                },
                "ix": 2
              },
              "nm": "e",
              "mn": "ADBE Vector Shape - Group",
              "hd": false
            },
            {
              "ty": "fl",
              "c": {
                "a": 0,
                "k": [0.501949953565, 0.670590030446, 1, 1],
                "ix": 4
              },
              "o": {
                "a": 0,
                "k": 100,
                "ix": 5
              },
              "r": 1,
              "bm": 0,
              "nm": "Fill 1",
              "mn": "ADBE Vector Graphic - Fill",
              "hd": false
            },
            {
              "ty": "st",
              "c": {
                "a": 0,
                "k": [0, 0, 0, 1],
                "ix": 3
              },
              "o": {
                "a": 0,
                "k": 100,
                "ix": 4
              },
              "w": {
                "a": 0,
                "k": 7,
                "ix": 5
              },
              "lc": 1,
              "lj": 1,
              "ml": 4,
              "bm": 0,
              "nm": "Stroke 1",
              "mn": "ADBE Vector Graphic - Stroke",
              "hd": false
            },
            {
              "ty": "tr",
              "p": {
                "a": 0,
                "k": [1161.609, -136.945],
                "ix": 2
              },
              "a": {
                "a": 0,
                "k": [1161.609, -136.945],
                "ix": 1
              },
              "s": {
                "a": 1,
                "k": [
                  {
                    "i": {
                      "x": [0.149, 0.149],
                      "y": [1, 1]
                    },
                    "o": {
                      "x": [0.333, 0.333],
                      "y": [0, 0]
                    },
                    "t": 8,
                    "s": [0, 0]
                  },
                  {
                    "i": {
                      "x": [0.667, 0.667],
                      "y": [1, 1]
                    },
                    "o": {
                      "x": [1, 1],
                      "y": [0, 0]
                    },
                    "t": 13,
                    "s": [120, 120]
                  },
                  {
                    "i": {
                      "x": [0.667, 0.667],
                      "y": [1, 1]
                    },
                    "o": {
                      "x": [0.333, 0.333],
                      "y": [0, 0]
                    },
                    "t": 18,
                    "s": [90, 90]
                  },
                  {
                    "i": {
                      "x": [0.667, 0.667],
                      "y": [1, 1]
                    },
                    "o": {
                      "x": [0.333, 0.333],
                      "y": [0, 0]
                    },
                    "t": 22,
                    "s": [105, 105]
                  },
                  {
                    "i": {
                      "x": [0.667, 0.667],
                      "y": [0.911, 0.911]
                    },
                    "o": {
                      "x": [0.333, 0.333],
                      "y": [0, 0]
                    },
                    "t": 26,
                    "s": [95, 95]
                  },
                  {
                    "t": 31,
                    "s": [100, 100]
                  }
                ],
                "ix": 3
              },
              "r": {
                "a": 0,
                "k": 0,
                "ix": 6
              },
              "o": {
                "a": 0,
                "k": 100,
                "ix": 7
              },
              "sk": {
                "a": 0,
                "k": 0,
                "ix": 4
              },
              "sa": {
                "a": 0,
                "k": 0,
                "ix": 5
              },
              "nm": "Transform"
            }
          ],
          "nm": "e",
          "np": 3,
          "cix": 2,
          "bm": 0,
          "ix": 9,
          "mn": "ADBE Vector Group",
          "hd": false
        }
      ],
      "ip": 0,
      "op": 83,
      "st": 0,
      "bm": 0
    },
    {
      "ddd": 0,
      "ind": 2,
      "ty": 4,
      "nm": "the huddle shadow outlines",
      "sr": 1,
      "ks": {
        "o": {
          "a": 0,
          "k": 100,
          "ix": 11
        },
        "r": {
          "a": 0,
          "k": 0,
          "ix": 10
        },
        "p": {
          "a": 0,
          "k": [734.5, 191.788, 0],
          "ix": 2
        },
        "a": {
          "a": 0,
          "k": [660.703, -129.712, 0],
          "ix": 1
        },
        "s": {
          "a": 0,
          "k": [100, 100, 100],
          "ix": 6
        }
      },
      "ao": 0,
      "shapes": [
        {
          "ty": "gr",
          "it": [
            {
              "ind": 0,
              "ty": "sh",
              "ix": 1,
              "ks": {
                "a": 0,
                "k": {
                  "i": [
                    [0, 0],
                    [0, 0],
                    [0, 0],
                    [0, 0],
                    [0, 0],
                    [0, 0],
                    [0, 0],
                    [0, 0]
                  ],
                  "o": [
                    [0, 0],
                    [0, 0],
                    [0, 0],
                    [0, 0],
                    [0, 0],
                    [0, 0],
                    [0, 0],
                    [0, 0]
                  ],
                  "v": [
                    [39.859, 0],
                    [92.392, 0],
                    [92.392, -227.977],
                    [131.305, -227.977],
                    [131.305, -275.144],
                    [0.946, -275.144],
                    [0.946, -227.977],
                    [39.859, -227.977]
                  ],
                  "c": true
                },
                "ix": 2
              },
              "nm": "t",
              "mn": "ADBE Vector Shape - Group",
              "hd": false
            },
            {
              "ty": "fl",
              "c": {
                "a": 0,
                "k": [0, 0, 0, 1],
                "ix": 4
              },
              "o": {
                "a": 0,
                "k": 100,
                "ix": 5
              },
              "r": 1,
              "bm": 0,
              "nm": "Fill 1",
              "mn": "ADBE Vector Graphic - Fill",
              "hd": false
            },
            {
              "ty": "tr",
              "p": {
                "a": 0,
                "k": [66.184, -137.495],
                "ix": 2
              },
              "a": {
                "a": 0,
                "k": [66.184, -137.495],
                "ix": 1
              },
              "s": {
                "a": 1,
                "k": [
                  {
                    "i": {
                      "x": [0.149, 0.149],
                      "y": [1, 1]
                    },
                    "o": {
                      "x": [0.333, 0.333],
                      "y": [0, 0]
                    },
                    "t": 0,
                    "s": [0, 0]
                  },
                  {
                    "i": {
                      "x": [0.667, 0.667],
                      "y": [1, 1]
                    },
                    "o": {
                      "x": [1, 1],
                      "y": [0, 0]
                    },
                    "t": 5,
                    "s": [120, 120]
                  },
                  {
                    "i": {
                      "x": [0.667, 0.667],
                      "y": [1, 1]
                    },
                    "o": {
                      "x": [0.333, 0.333],
                      "y": [0, 0]
                    },
                    "t": 10,
                    "s": [90, 90]
                  },
                  {
                    "i": {
                      "x": [0.667, 0.667],
                      "y": [1, 1]
                    },
                    "o": {
                      "x": [0.333, 0.333],
                      "y": [0, 0]
                    },
                    "t": 14,
                    "s": [105, 105]
                  },
                  {
                    "i": {
                      "x": [0.667, 0.667],
                      "y": [0.911, 0.911]
                    },
                    "o": {
                      "x": [0.333, 0.333],
                      "y": [0, 0]
                    },
                    "t": 18,
                    "s": [95, 95]
                  },
                  {
                    "t": 23,
                    "s": [100, 100]
                  }
                ],
                "ix": 3
              },
              "r": {
                "a": 0,
                "k": 0,
                "ix": 6
              },
              "o": {
                "a": 0,
                "k": 100,
                "ix": 7
              },
              "sk": {
                "a": 0,
                "k": 0,
                "ix": 4
              },
              "sa": {
                "a": 0,
                "k": 0,
                "ix": 5
              },
              "nm": "Transform"
            }
          ],
          "nm": "t",
          "np": 3,
          "cix": 2,
          "bm": 0,
          "ix": 1,
          "mn": "ADBE Vector Group",
          "hd": false
        },
        {
          "ty": "gr",
          "it": [
            {
              "ind": 0,
              "ty": "sh",
              "ix": 1,
              "ks": {
                "a": 0,
                "k": {
                  "i": [
                    [0, 0],
                    [0, 0],
                    [0, 0],
                    [0, 0],
                    [0, 0],
                    [0, 0],
                    [0, 0],
                    [0, 0],
                    [0, 0],
                    [0, 0],
                    [0, 0],
                    [0, 0]
                  ],
                  "o": [
                    [0, 0],
                    [0, 0],
                    [0, 0],
                    [0, 0],
                    [0, 0],
                    [0, 0],
                    [0, 0],
                    [0, 0],
                    [0, 0],
                    [0, 0],
                    [0, 0],
                    [0, 0]
                  ],
                  "v": [
                    [137.407, 0],
                    [189.94, 0],
                    [189.94, -113.988],
                    [209.396, -113.988],
                    [209.396, 0],
                    [261.929, 0],
                    [261.929, -275.144],
                    [209.396, -275.144],
                    [209.396, -161.156],
                    [189.94, -161.156],
                    [189.94, -275.144],
                    [137.407, -275.144]
                  ],
                  "c": true
                },
                "ix": 2
              },
              "nm": "h",
              "mn": "ADBE Vector Shape - Group",
              "hd": false
            },
            {
              "ty": "fl",
              "c": {
                "a": 0,
                "k": [0, 0, 0, 1],
                "ix": 4
              },
              "o": {
                "a": 0,
                "k": 100,
                "ix": 5
              },
              "r": 1,
              "bm": 0,
              "nm": "Fill 1",
              "mn": "ADBE Vector Graphic - Fill",
              "hd": false
            },
            {
              "ty": "tr",
              "p": {
                "a": 0,
                "k": [200.246, -137.562],
                "ix": 2
              },
              "a": {
                "a": 0,
                "k": [200.246, -137.562],
                "ix": 1
              },
              "s": {
                "a": 1,
                "k": [
                  {
                    "i": {
                      "x": [0.149, 0.149],
                      "y": [1, 1]
                    },
                    "o": {
                      "x": [0.333, 0.333],
                      "y": [0, 0]
                    },
                    "t": 1,
                    "s": [0, 0]
                  },
                  {
                    "i": {
                      "x": [0.667, 0.667],
                      "y": [1, 1]
                    },
                    "o": {
                      "x": [1, 1],
                      "y": [0, 0]
                    },
                    "t": 6,
                    "s": [120, 120]
                  },
                  {
                    "i": {
                      "x": [0.667, 0.667],
                      "y": [1, 1]
                    },
                    "o": {
                      "x": [0.333, 0.333],
                      "y": [0, 0]
                    },
                    "t": 11,
                    "s": [90, 90]
                  },
                  {
                    "i": {
                      "x": [0.667, 0.667],
                      "y": [1, 1]
                    },
                    "o": {
                      "x": [0.333, 0.333],
                      "y": [0, 0]
                    },
                    "t": 15,
                    "s": [105, 105]
                  },
                  {
                    "i": {
                      "x": [0.667, 0.667],
                      "y": [0.911, 0.911]
                    },
                    "o": {
                      "x": [0.333, 0.333],
                      "y": [0, 0]
                    },
                    "t": 19,
                    "s": [95, 95]
                  },
                  {
                    "t": 24,
                    "s": [100, 100]
                  }
                ],
                "ix": 3
              },
              "r": {
                "a": 0,
                "k": 0,
                "ix": 6
              },
              "o": {
                "a": 0,
                "k": 100,
                "ix": 7
              },
              "sk": {
                "a": 0,
                "k": 0,
                "ix": 4
              },
              "sa": {
                "a": 0,
                "k": 0,
                "ix": 5
              },
              "nm": "Transform"
            }
          ],
          "nm": "h",
          "np": 3,
          "cix": 2,
          "bm": 0,
          "ix": 2,
          "mn": "ADBE Vector Group",
          "hd": false
        },
        {
          "ty": "gr",
          "it": [
            {
              "ind": 0,
              "ty": "sh",
              "ix": 1,
              "ks": {
                "a": 0,
                "k": {
                  "i": [
                    [0, 0],
                    [0, 0],
                    [0, 0],
                    [0, 0],
                    [0, 0],
                    [0, 0],
                    [0, 0],
                    [0, 0],
                    [0, 0],
                    [0, 0],
                    [0, 0],
                    [0, 0]
                  ],
                  "o": [
                    [0, 0],
                    [0, 0],
                    [0, 0],
                    [0, 0],
                    [0, 0],
                    [0, 0],
                    [0, 0],
                    [0, 0],
                    [0, 0],
                    [0, 0],
                    [0, 0],
                    [0, 0]
                  ],
                  "v": [
                    [277.665, 0],
                    [378.839, 0],
                    [378.839, -47.168],
                    [330.198, -47.168],
                    [330.198, -117.919],
                    [365.22, -117.919],
                    [365.22, -165.087],
                    [330.198, -165.087],
                    [330.198, -227.977],
                    [378.839, -227.977],
                    [378.839, -275.144],
                    [277.665, -275.144]
                  ],
                  "c": true
                },
                "ix": 2
              },
              "nm": "e",
              "mn": "ADBE Vector Shape - Group",
              "hd": false
            },
            {
              "ty": "fl",
              "c": {
                "a": 0,
                "k": [0, 0, 0, 1],
                "ix": 4
              },
              "o": {
                "a": 0,
                "k": 100,
                "ix": 5
              },
              "r": 1,
              "bm": 0,
              "nm": "Fill 1",
              "mn": "ADBE Vector Graphic - Fill",
              "hd": false
            },
            {
              "ty": "tr",
              "p": {
                "a": 0,
                "k": [328.255, -137.489],
                "ix": 2
              },
              "a": {
                "a": 0,
                "k": [328.255, -137.489],
                "ix": 1
              },
              "s": {
                "a": 1,
                "k": [
                  {
                    "i": {
                      "x": [0.149, 0.149],
                      "y": [1, 1]
                    },
                    "o": {
                      "x": [0.333, 0.333],
                      "y": [0, 0]
                    },
                    "t": 2,
                    "s": [0, 0]
                  },
                  {
                    "i": {
                      "x": [0.667, 0.667],
                      "y": [1, 1]
                    },
                    "o": {
                      "x": [1, 1],
                      "y": [0, 0]
                    },
                    "t": 7,
                    "s": [120, 120]
                  },
                  {
                    "i": {
                      "x": [0.667, 0.667],
                      "y": [1, 1]
                    },
                    "o": {
                      "x": [0.333, 0.333],
                      "y": [0, 0]
                    },
                    "t": 12,
                    "s": [90, 90]
                  },
                  {
                    "i": {
                      "x": [0.667, 0.667],
                      "y": [1, 1]
                    },
                    "o": {
                      "x": [0.333, 0.333],
                      "y": [0, 0]
                    },
                    "t": 16,
                    "s": [105, 105]
                  },
                  {
                    "i": {
                      "x": [0.667, 0.667],
                      "y": [0.911, 0.911]
                    },
                    "o": {
                      "x": [0.333, 0.333],
                      "y": [0, 0]
                    },
                    "t": 20,
                    "s": [95, 95]
                  },
                  {
                    "t": 25,
                    "s": [100, 100]
                  }
                ],
                "ix": 3
              },
              "r": {
                "a": 0,
                "k": 0,
                "ix": 6
              },
              "o": {
                "a": 0,
                "k": 100,
                "ix": 7
              },
              "sk": {
                "a": 0,
                "k": 0,
                "ix": 4
              },
              "sa": {
                "a": 0,
                "k": 0,
                "ix": 5
              },
              "nm": "Transform"
            }
          ],
          "nm": "e",
          "np": 3,
          "cix": 2,
          "bm": 0,
          "ix": 3,
          "mn": "ADBE Vector Group",
          "hd": false
        },
        {
          "ty": "gr",
          "it": [
            {
              "ind": 0,
              "ty": "sh",
              "ix": 1,
              "ks": {
                "a": 0,
                "k": {
                  "i": [
                    [0, 0],
                    [0, 0],
                    [0, 0],
                    [0, 0],
                    [0, 0],
                    [0, 0],
                    [0, 0],
                    [0, 0],
                    [0, 0],
                    [0, 0],
                    [0, 0],
                    [0, 0]
                  ],
                  "o": [
                    [0, 0],
                    [0, 0],
                    [0, 0],
                    [0, 0],
                    [0, 0],
                    [0, 0],
                    [0, 0],
                    [0, 0],
                    [0, 0],
                    [0, 0],
                    [0, 0],
                    [0, 0]
                  ],
                  "v": [
                    [442.267, 0],
                    [494.8, 0],
                    [494.8, -113.988],
                    [514.256, -113.988],
                    [514.256, 0],
                    [566.789, 0],
                    [566.789, -275.144],
                    [514.256, -275.144],
                    [514.256, -161.156],
                    [494.8, -161.156],
                    [494.8, -275.144],
                    [442.267, -275.144]
                  ],
                  "c": true
                },
                "ix": 2
              },
              "nm": "h",
              "mn": "ADBE Vector Shape - Group",
              "hd": false
            },
            {
              "ty": "fl",
              "c": {
                "a": 0,
                "k": [0, 0, 0, 1],
                "ix": 4
              },
              "o": {
                "a": 0,
                "k": 100,
                "ix": 5
              },
              "r": 1,
              "bm": 0,
              "nm": "Fill 1",
              "mn": "ADBE Vector Graphic - Fill",
              "hd": false
            },
            {
              "ty": "tr",
              "p": {
                "a": 0,
                "k": [505.253, -137.501],
                "ix": 2
              },
              "a": {
                "a": 0,
                "k": [505.253, -137.501],
                "ix": 1
              },
              "s": {
                "a": 1,
                "k": [
                  {
                    "i": {
                      "x": [0.149, 0.149],
                      "y": [1, 1]
                    },
                    "o": {
                      "x": [0.333, 0.333],
                      "y": [0, 0]
                    },
                    "t": 3,
                    "s": [0, 0]
                  },
                  {
                    "i": {
                      "x": [0.667, 0.667],
                      "y": [1, 1]
                    },
                    "o": {
                      "x": [1, 1],
                      "y": [0, 0]
                    },
                    "t": 8,
                    "s": [120, 120]
                  },
                  {
                    "i": {
                      "x": [0.667, 0.667],
                      "y": [1, 1]
                    },
                    "o": {
                      "x": [0.333, 0.333],
                      "y": [0, 0]
                    },
                    "t": 13,
                    "s": [90, 90]
                  },
                  {
                    "i": {
                      "x": [0.667, 0.667],
                      "y": [1, 1]
                    },
                    "o": {
                      "x": [0.333, 0.333],
                      "y": [0, 0]
                    },
                    "t": 17,
                    "s": [105, 105]
                  },
                  {
                    "i": {
                      "x": [0.667, 0.667],
                      "y": [0.911, 0.911]
                    },
                    "o": {
                      "x": [0.333, 0.333],
                      "y": [0, 0]
                    },
                    "t": 21,
                    "s": [95, 95]
                  },
                  {
                    "t": 26,
                    "s": [100, 100]
                  }
                ],
                "ix": 3
              },
              "r": {
                "a": 0,
                "k": 0,
                "ix": 6
              },
              "o": {
                "a": 0,
                "k": 100,
                "ix": 7
              },
              "sk": {
                "a": 0,
                "k": 0,
                "ix": 4
              },
              "sa": {
                "a": 0,
                "k": 0,
                "ix": 5
              },
              "nm": "Transform"
            }
          ],
          "nm": "h",
          "np": 3,
          "cix": 2,
          "bm": 0,
          "ix": 4,
          "mn": "ADBE Vector Group",
          "hd": false
        },
        {
          "ty": "gr",
          "it": [
            {
              "ind": 0,
              "ty": "sh",
              "ix": 1,
              "ks": {
                "a": 0,
                "k": {
                  "i": [
                    [-35.022, 0],
                    [0, 66.821],
                    [0, 0],
                    [0, 0],
                    [0, 0],
                    [5.837, 0],
                    [0, 35.376],
                    [0, 0],
                    [0, 0],
                    [0, 0]
                  ],
                  "o": [
                    [35.022, 0],
                    [0, 0],
                    [0, 0],
                    [0, 0],
                    [0, 35.376],
                    [-5.837, 0],
                    [0, 0],
                    [0, 0],
                    [0, 0],
                    [0, 66.821]
                  ],
                  "v": [
                    [644.786, 5.896],
                    [707.047, -88.439],
                    [707.047, -275.144],
                    [654.514, -275.144],
                    [654.514, -76.647],
                    [644.786, -37.341],
                    [635.058, -76.647],
                    [635.058, -275.144],
                    [582.525, -275.144],
                    [582.525, -88.439]
                  ],
                  "c": true
                },
                "ix": 2
              },
              "nm": "u",
              "mn": "ADBE Vector Shape - Group",
              "hd": false
            },
            {
              "ty": "fl",
              "c": {
                "a": 0,
                "k": [0, 0, 0, 1],
                "ix": 4
              },
              "o": {
                "a": 0,
                "k": 100,
                "ix": 5
              },
              "r": 1,
              "bm": 0,
              "nm": "Fill 1",
              "mn": "ADBE Vector Graphic - Fill",
              "hd": false
            },
            {
              "ty": "tr",
              "p": {
                "a": 0,
                "k": [645.224, -134.574],
                "ix": 2
              },
              "a": {
                "a": 0,
                "k": [645.224, -134.574],
                "ix": 1
              },
              "s": {
                "a": 1,
                "k": [
                  {
                    "i": {
                      "x": [0.149, 0.149],
                      "y": [1, 1]
                    },
                    "o": {
                      "x": [0.333, 0.333],
                      "y": [0, 0]
                    },
                    "t": 4,
                    "s": [0, 0]
                  },
                  {
                    "i": {
                      "x": [0.667, 0.667],
                      "y": [1, 1]
                    },
                    "o": {
                      "x": [1, 1],
                      "y": [0, 0]
                    },
                    "t": 9,
                    "s": [120, 120]
                  },
                  {
                    "i": {
                      "x": [0.667, 0.667],
                      "y": [1, 1]
                    },
                    "o": {
                      "x": [0.333, 0.333],
                      "y": [0, 0]
                    },
                    "t": 14,
                    "s": [90, 90]
                  },
                  {
                    "i": {
                      "x": [0.667, 0.667],
                      "y": [1, 1]
                    },
                    "o": {
                      "x": [0.333, 0.333],
                      "y": [0, 0]
                    },
                    "t": 18,
                    "s": [105, 105]
                  },
                  {
                    "i": {
                      "x": [0.667, 0.667],
                      "y": [0.911, 0.911]
                    },
                    "o": {
                      "x": [0.333, 0.333],
                      "y": [0, 0]
                    },
                    "t": 22,
                    "s": [95, 95]
                  },
                  {
                    "t": 27,
                    "s": [100, 100]
                  }
                ],
                "ix": 3
              },
              "r": {
                "a": 0,
                "k": 0,
                "ix": 6
              },
              "o": {
                "a": 0,
                "k": 100,
                "ix": 7
              },
              "sk": {
                "a": 0,
                "k": 0,
                "ix": 4
              },
              "sa": {
                "a": 0,
                "k": 0,
                "ix": 5
              },
              "nm": "Transform"
            }
          ],
          "nm": "u",
          "np": 3,
          "cix": 2,
          "bm": 0,
          "ix": 5,
          "mn": "ADBE Vector Group",
          "hd": false
        },
        {
          "ty": "gr",
          "it": [
            {
              "ind": 0,
              "ty": "sh",
              "ix": 1,
              "ks": {
                "a": 0,
                "k": {
                  "i": [
                    [0, 0],
                    [0, 0],
                    [0, 104.162],
                    [42.805, 0],
                    [0, 0]
                  ],
                  "o": [
                    [0, 0],
                    [42.805, 0],
                    [0, -104.162],
                    [0, 0],
                    [0, 0]
                  ],
                  "v": [
                    [722.783, 0],
                    [775.316, 0],
                    [851.197, -137.572],
                    [775.316, -275.144],
                    [722.783, -275.144]
                  ],
                  "c": true
                },
                "ix": 2
              },
              "nm": "d",
              "mn": "ADBE Vector Shape - Group",
              "hd": false
            },
            {
              "ind": 1,
              "ty": "sh",
              "ix": 2,
              "ks": {
                "a": 0,
                "k": {
                  "i": [
                    [0, 0],
                    [0, 0],
                    [0, 0],
                    [0, -86.474],
                    [9.728, 0]
                  ],
                  "o": [
                    [0, 0],
                    [0, 0],
                    [9.728, 0],
                    [0, 86.474],
                    [0, 0]
                  ],
                  "v": [
                    [775.316, -43.237],
                    [775.316, -231.907],
                    [777.261, -231.907],
                    [794.772, -137.572],
                    [777.261, -43.237]
                  ],
                  "c": true
                },
                "ix": 2
              },
              "nm": "d",
              "mn": "ADBE Vector Shape - Group",
              "hd": false
            },
            {
              "ty": "mm",
              "mm": 1,
              "nm": "Merge Paths 1",
              "mn": "ADBE Vector Filter - Merge",
              "hd": false
            },
            {
              "ty": "fl",
              "c": {
                "a": 0,
                "k": [0, 0, 0, 1],
                "ix": 4
              },
              "o": {
                "a": 0,
                "k": 100,
                "ix": 5
              },
              "r": 1,
              "bm": 0,
              "nm": "Fill 1",
              "mn": "ADBE Vector Graphic - Fill",
              "hd": false
            },
            {
              "ty": "tr",
              "p": {
                "a": 0,
                "k": [787.146, -137.467],
                "ix": 2
              },
              "a": {
                "a": 0,
                "k": [787.146, -137.467],
                "ix": 1
              },
              "s": {
                "a": 1,
                "k": [
                  {
                    "i": {
                      "x": [0.149, 0.149],
                      "y": [1, 1]
                    },
                    "o": {
                      "x": [0.333, 0.333],
                      "y": [0, 0]
                    },
                    "t": 5,
                    "s": [0, 0]
                  },
                  {
                    "i": {
                      "x": [0.667, 0.667],
                      "y": [1, 1]
                    },
                    "o": {
                      "x": [1, 1],
                      "y": [0, 0]
                    },
                    "t": 10,
                    "s": [120, 120]
                  },
                  {
                    "i": {
                      "x": [0.667, 0.667],
                      "y": [1, 1]
                    },
                    "o": {
                      "x": [0.333, 0.333],
                      "y": [0, 0]
                    },
                    "t": 15,
                    "s": [90, 90]
                  },
                  {
                    "i": {
                      "x": [0.667, 0.667],
                      "y": [1, 1]
                    },
                    "o": {
                      "x": [0.333, 0.333],
                      "y": [0, 0]
                    },
                    "t": 19,
                    "s": [105, 105]
                  },
                  {
                    "i": {
                      "x": [0.667, 0.667],
                      "y": [0.911, 0.911]
                    },
                    "o": {
                      "x": [0.333, 0.333],
                      "y": [0, 0]
                    },
                    "t": 23,
                    "s": [95, 95]
                  },
                  {
                    "t": 28,
                    "s": [100, 100]
                  }
                ],
                "ix": 3
              },
              "r": {
                "a": 0,
                "k": 0,
                "ix": 6
              },
              "o": {
                "a": 0,
                "k": 100,
                "ix": 7
              },
              "sk": {
                "a": 0,
                "k": 0,
                "ix": 4
              },
              "sa": {
                "a": 0,
                "k": 0,
                "ix": 5
              },
              "nm": "Transform"
            }
          ],
          "nm": "d",
          "np": 5,
          "cix": 2,
          "bm": 0,
          "ix": 6,
          "mn": "ADBE Vector Group",
          "hd": false
        },
        {
          "ty": "gr",
          "it": [
            {
              "ind": 0,
              "ty": "sh",
              "ix": 1,
              "ks": {
                "a": 0,
                "k": {
                  "i": [
                    [0, 0],
                    [0, 0],
                    [0, 104.162],
                    [42.805, 0],
                    [0, 0]
                  ],
                  "o": [
                    [0, 0],
                    [42.805, 0],
                    [0, -104.162],
                    [0, 0],
                    [0, 0]
                  ],
                  "v": [
                    [863.041, 0],
                    [915.574, 0],
                    [991.455, -137.572],
                    [915.574, -275.144],
                    [863.041, -275.144]
                  ],
                  "c": true
                },
                "ix": 2
              },
              "nm": "d",
              "mn": "ADBE Vector Shape - Group",
              "hd": false
            },
            {
              "ind": 1,
              "ty": "sh",
              "ix": 2,
              "ks": {
                "a": 0,
                "k": {
                  "i": [
                    [0, 0],
                    [0, 0],
                    [0, 0],
                    [0, -86.474],
                    [9.728, 0]
                  ],
                  "o": [
                    [0, 0],
                    [0, 0],
                    [9.728, 0],
                    [0, 86.474],
                    [0, 0]
                  ],
                  "v": [
                    [915.574, -43.237],
                    [915.574, -231.907],
                    [917.52, -231.907],
                    [935.031, -137.572],
                    [917.52, -43.237]
                  ],
                  "c": true
                },
                "ix": 2
              },
              "nm": "d",
              "mn": "ADBE Vector Shape - Group",
              "hd": false
            },
            {
              "ty": "mm",
              "mm": 1,
              "nm": "Merge Paths 1",
              "mn": "ADBE Vector Filter - Merge",
              "hd": false
            },
            {
              "ty": "fl",
              "c": {
                "a": 0,
                "k": [0, 0, 0, 1],
                "ix": 4
              },
              "o": {
                "a": 0,
                "k": 100,
                "ix": 5
              },
              "r": 1,
              "bm": 0,
              "nm": "Fill 1",
              "mn": "ADBE Vector Graphic - Fill",
              "hd": false
            },
            {
              "ty": "tr",
              "p": {
                "a": 0,
                "k": [927.154, -137.608],
                "ix": 2
              },
              "a": {
                "a": 0,
                "k": [927.154, -137.608],
                "ix": 1
              },
              "s": {
                "a": 1,
                "k": [
                  {
                    "i": {
                      "x": [0.149, 0.149],
                      "y": [1, 1]
                    },
                    "o": {
                      "x": [0.333, 0.333],
                      "y": [0, 0]
                    },
                    "t": 6,
                    "s": [0, 0]
                  },
                  {
                    "i": {
                      "x": [0.667, 0.667],
                      "y": [1, 1]
                    },
                    "o": {
                      "x": [1, 1],
                      "y": [0, 0]
                    },
                    "t": 11,
                    "s": [120, 120]
                  },
                  {
                    "i": {
                      "x": [0.667, 0.667],
                      "y": [1, 1]
                    },
                    "o": {
                      "x": [0.333, 0.333],
                      "y": [0, 0]
                    },
                    "t": 16,
                    "s": [90, 90]
                  },
                  {
                    "i": {
                      "x": [0.667, 0.667],
                      "y": [1, 1]
                    },
                    "o": {
                      "x": [0.333, 0.333],
                      "y": [0, 0]
                    },
                    "t": 20,
                    "s": [105, 105]
                  },
                  {
                    "i": {
                      "x": [0.667, 0.667],
                      "y": [0.911, 0.911]
                    },
                    "o": {
                      "x": [0.333, 0.333],
                      "y": [0, 0]
                    },
                    "t": 24,
                    "s": [95, 95]
                  },
                  {
                    "t": 29,
                    "s": [100, 100]
                  }
                ],
                "ix": 3
              },
              "r": {
                "a": 0,
                "k": 0,
                "ix": 6
              },
              "o": {
                "a": 0,
                "k": 100,
                "ix": 7
              },
              "sk": {
                "a": 0,
                "k": 0,
                "ix": 4
              },
              "sa": {
                "a": 0,
                "k": 0,
                "ix": 5
              },
              "nm": "Transform"
            }
          ],
          "nm": "d",
          "np": 5,
          "cix": 2,
          "bm": 0,
          "ix": 7,
          "mn": "ADBE Vector Group",
          "hd": false
        },
        {
          "ty": "gr",
          "it": [
            {
              "ind": 0,
              "ty": "sh",
              "ix": 1,
              "ks": {
                "a": 0,
                "k": {
                  "i": [
                    [0, 0],
                    [0, 0],
                    [0, 0],
                    [0, 0],
                    [0, 0],
                    [0, 0]
                  ],
                  "o": [
                    [0, 0],
                    [0, 0],
                    [0, 0],
                    [0, 0],
                    [0, 0],
                    [0, 0]
                  ],
                  "v": [
                    [1003.299, 0],
                    [1106.419, 0],
                    [1106.419, -47.168],
                    [1055.832, -47.168],
                    [1055.832, -275.144],
                    [1003.299, -275.144]
                  ],
                  "c": true
                },
                "ix": 2
              },
              "nm": "l",
              "mn": "ADBE Vector Shape - Group",
              "hd": false
            },
            {
              "ty": "fl",
              "c": {
                "a": 0,
                "k": [0, 0, 0, 1],
                "ix": 4
              },
              "o": {
                "a": 0,
                "k": 100,
                "ix": 5
              },
              "r": 1,
              "bm": 0,
              "nm": "Fill 1",
              "mn": "ADBE Vector Graphic - Fill",
              "hd": false
            },
            {
              "ty": "tr",
              "p": {
                "a": 0,
                "k": [1055.138, -137.526],
                "ix": 2
              },
              "a": {
                "a": 0,
                "k": [1055.138, -137.526],
                "ix": 1
              },
              "s": {
                "a": 1,
                "k": [
                  {
                    "i": {
                      "x": [0.149, 0.149],
                      "y": [1, 1]
                    },
                    "o": {
                      "x": [0.333, 0.333],
                      "y": [0, 0]
                    },
                    "t": 7,
                    "s": [0, 0]
                  },
                  {
                    "i": {
                      "x": [0.667, 0.667],
                      "y": [1, 1]
                    },
                    "o": {
                      "x": [1, 1],
                      "y": [0, 0]
                    },
                    "t": 12,
                    "s": [120, 120]
                  },
                  {
                    "i": {
                      "x": [0.667, 0.667],
                      "y": [1, 1]
                    },
                    "o": {
                      "x": [0.333, 0.333],
                      "y": [0, 0]
                    },
                    "t": 17,
                    "s": [90, 90]
                  },
                  {
                    "i": {
                      "x": [0.667, 0.667],
                      "y": [1, 1]
                    },
                    "o": {
                      "x": [0.333, 0.333],
                      "y": [0, 0]
                    },
                    "t": 21,
                    "s": [105, 105]
                  },
                  {
                    "i": {
                      "x": [0.667, 0.667],
                      "y": [0.911, 0.911]
                    },
                    "o": {
                      "x": [0.333, 0.333],
                      "y": [0, 0]
                    },
                    "t": 25,
                    "s": [95, 95]
                  },
                  {
                    "t": 30,
                    "s": [100, 100]
                  }
                ],
                "ix": 3
              },
              "r": {
                "a": 0,
                "k": 0,
                "ix": 6
              },
              "o": {
                "a": 0,
                "k": 100,
                "ix": 7
              },
              "sk": {
                "a": 0,
                "k": 0,
                "ix": 4
              },
              "sa": {
                "a": 0,
                "k": 0,
                "ix": 5
              },
              "nm": "Transform"
            }
          ],
          "nm": "l",
          "np": 3,
          "cix": 2,
          "bm": 0,
          "ix": 8,
          "mn": "ADBE Vector Group",
          "hd": false
        },
        {
          "ty": "gr",
          "it": [
            {
              "ind": 0,
              "ty": "sh",
              "ix": 1,
              "ks": {
                "a": 0,
                "k": {
                  "i": [
                    [0, 0],
                    [0, 0],
                    [0, 0],
                    [0, 0],
                    [0, 0],
                    [0, 0],
                    [0, 0],
                    [0, 0],
                    [0, 0],
                    [0, 0],
                    [0, 0],
                    [0, 0]
                  ],
                  "o": [
                    [0, 0],
                    [0, 0],
                    [0, 0],
                    [0, 0],
                    [0, 0],
                    [0, 0],
                    [0, 0],
                    [0, 0],
                    [0, 0],
                    [0, 0],
                    [0, 0],
                    [0, 0]
                  ],
                  "v": [
                    [1112.645, 0],
                    [1213.819, 0],
                    [1213.819, -47.168],
                    [1165.178, -47.168],
                    [1165.178, -117.919],
                    [1200.2, -117.919],
                    [1200.2, -165.087],
                    [1165.178, -165.087],
                    [1165.178, -227.977],
                    [1213.819, -227.977],
                    [1213.819, -275.144],
                    [1112.645, -275.144]
                  ],
                  "c": true
                },
                "ix": 2
              },
              "nm": "e",
              "mn": "ADBE Vector Shape - Group",
              "hd": false
            },
            {
              "ty": "fl",
              "c": {
                "a": 0,
                "k": [0, 0, 0, 1],
                "ix": 4
              },
              "o": {
                "a": 0,
                "k": 100,
                "ix": 5
              },
              "r": 1,
              "bm": 0,
              "nm": "Fill 1",
              "mn": "ADBE Vector Graphic - Fill",
              "hd": false
            },
            {
              "ty": "tr",
              "p": {
                "a": 0,
                "k": [1163.26, -137.58],
                "ix": 2
              },
              "a": {
                "a": 0,
                "k": [1163.26, -137.58],
                "ix": 1
              },
              "s": {
                "a": 1,
                "k": [
                  {
                    "i": {
                      "x": [0.149, 0.149],
                      "y": [1, 1]
                    },
                    "o": {
                      "x": [0.333, 0.333],
                      "y": [0, 0]
                    },
                    "t": 8,
                    "s": [0, 0]
                  },
                  {
                    "i": {
                      "x": [0.667, 0.667],
                      "y": [1, 1]
                    },
                    "o": {
                      "x": [1, 1],
                      "y": [0, 0]
                    },
                    "t": 13,
                    "s": [120, 120]
                  },
                  {
                    "i": {
                      "x": [0.667, 0.667],
                      "y": [1, 1]
                    },
                    "o": {
                      "x": [0.333, 0.333],
                      "y": [0, 0]
                    },
                    "t": 18,
                    "s": [90, 90]
                  },
                  {
                    "i": {
                      "x": [0.667, 0.667],
                      "y": [1, 1]
                    },
                    "o": {
                      "x": [0.333, 0.333],
                      "y": [0, 0]
                    },
                    "t": 22,
                    "s": [105, 105]
                  },
                  {
                    "i": {
                      "x": [0.667, 0.667],
                      "y": [0.911, 0.911]
                    },
                    "o": {
                      "x": [0.333, 0.333],
                      "y": [0, 0]
                    },
                    "t": 26,
                    "s": [95, 95]
                  },
                  {
                    "t": 31,
                    "s": [100, 100]
                  }
                ],
                "ix": 3
              },
              "r": {
                "a": 0,
                "k": 0,
                "ix": 6
              },
              "o": {
                "a": 0,
                "k": 100,
                "ix": 7
              },
              "sk": {
                "a": 0,
                "k": 0,
                "ix": 4
              },
              "sa": {
                "a": 0,
                "k": 0,
                "ix": 5
              },
              "nm": "Transform"
            }
          ],
          "nm": "e",
          "np": 3,
          "cix": 2,
          "bm": 0,
          "ix": 9,
          "mn": "ADBE Vector Group",
          "hd": false
        }
      ],
      "ip": 0,
      "op": 83,
      "st": 0,
      "bm": 0
    }
  ],
  "markers": []
}
